scrapy_rnet/__init__.py
scrapy_rnet/handler.py
scrapy_rnet/parser.py
scrapy_rnet-0.0.5.dist-info/METADATA
scrapy_rnet-0.0.5.dist-info/WHEEL
scrapy_rnet-0.0.5.dist-info/top_level.txt
scrapy_rnet-0.0.5.dist-info/RECORD
