Metadata-Version: 2.4
Name: scrapy-rnet
Version: 0.0.5
Requires-Python: >=3.12
Requires-Dist: rnet>=2.1.0
Requires-Dist: scrapy>=2.12.0
